omam_authkit/__init__.py
omam_authkit/client.py
omam_authkit/exceptions.py
omam_authkit/token_manager.py
omam_authkit/django/__init__.py
omam_authkit/django/decorators.py
omam_authkit/django/middleware.py
omam_authkit/django/urls.py
omam_authkit/django/utils.py
omam_authkit/django/views.py
omam_authkit/storage/__init__.py
omam_authkit/storage/secure_storage.py
omam_authkit/webhooks/__init__.py
omam_authkit/webhooks/handler.py
omam_authkit-0.1.0.dist-info/licenses/LICENSE
omam_authkit-0.1.0.dist-info/METADATA
omam_authkit-0.1.0.dist-info/WHEEL
omam_authkit-0.1.0.dist-info/top_level.txt
omam_authkit-0.1.0.dist-info/RECORD
