Metadata-Version: 2.4
Name: omam-authkit
Version: 0.1.0
Summary: Python SDK for Omam AuthKit - OAuth 2.0 authentication provider
Home-page: https://github.com/hamashoool/omam-authkit-python-sdk
Author: Osman
Author-email: Osman <osman@hamashool.com>
License: MIT
Project-URL: Homepage, https://github.com/hamashoool/omam-authkit-python-sdk
Project-URL: Documentation, https://github.com/hamashoool/omam-authkit-python-sdk
Project-URL: Repository, https://github.com/hamashoool/omam-authkit-python-sdk
Classifier: Development Status :: 4 - Beta
Classifier: Intended Audience :: Developers
Classifier: License :: OSI Approved :: MIT License
Classifier: Programming Language :: Python :: 3
Classifier: Programming Language :: Python :: 3.8
Classifier: Programming Language :: Python :: 3.9
Classifier: Programming Language :: Python :: 3.10
Classifier: Programming Language :: Python :: 3.11
Classifier: Programming Language :: Python :: 3.12
Requires-Python: >=3.8
License-File: LICENSE
Requires-Dist: requests>=2.28.0
Requires-Dist: cryptography>=41.0.0
Requires-Dist: PyJWT>=2.8.0
Provides-Extra: django
Requires-Dist: Django>=3.2; extra == "django"
Provides-Extra: dev
Requires-Dist: pytest>=7.0.0; extra == "dev"
Requires-Dist: pytest-cov>=4.0.0; extra == "dev"
Requires-Dist: black>=23.0.0; extra == "dev"
Requires-Dist: flake8>=6.0.0; extra == "dev"
Requires-Dist: mypy>=1.0.0; extra == "dev"
Dynamic: author
Dynamic: home-page
Dynamic: license-file
Dynamic: requires-python
